morepath/__init__.py
morepath/app.py
morepath/authentication.py
morepath/autosetup.py
morepath/converter.py
morepath/core.py
morepath/directive.py
morepath/error.py
morepath/mapply.py
morepath/path.py
morepath/pdbsupport.py
morepath/predicate.py
morepath/publish.py
morepath/reify.py
morepath/request.py
morepath/run.py
morepath/settings.py
morepath/template.py
morepath/toposort.py
morepath/traject.py
morepath/tween.py
morepath/view.py
morepath/tests/__init__.py
morepath/tests/capturelog.py
morepath/tests/conftest.py
morepath/tests/test_autosetup.py
morepath/tests/test_capturelog.py
morepath/tests/test_cleanup.py
morepath/tests/test_code_info.py
morepath/tests/test_config_logging.py
morepath/tests/test_converter.py
morepath/tests/test_defer_links.py
morepath/tests/test_directive.py
morepath/tests/test_error.py
morepath/tests/test_excview.py
morepath/tests/test_extend.py
morepath/tests/test_init_settings.py
morepath/tests/test_internal.py
morepath/tests/test_json_obj.py
morepath/tests/test_link.py
morepath/tests/test_load.py
morepath/tests/test_mapply.py
morepath/tests/test_method_directive.py
morepath/tests/test_model.py
morepath/tests/test_mount_directive.py
morepath/tests/test_path_directive.py
morepath/tests/test_predicate.py
morepath/tests/test_predicates.py
morepath/tests/test_publish.py
morepath/tests/test_querytool.py
morepath/tests/test_reify.py
morepath/tests/test_request.py
morepath/tests/test_run.py
morepath/tests/test_scanning.py
morepath/tests/test_scenario.py
morepath/tests/test_security.py
morepath/tests/test_setting_directive.py
morepath/tests/test_template.py
morepath/tests/test_toposort.py
morepath/tests/test_traject.py
morepath/tests/test_tween.py
morepath/tests/test_view_directive.py
morepath/tests/fixtures/__init__.py
morepath/tests/fixtures/abbr.py
morepath/tests/fixtures/basic.py
morepath/tests/fixtures/conflict.py
morepath/tests/fixtures/conflicterror.py
morepath/tests/fixtures/identity_policy.py
morepath/tests/fixtures/mapply_bug.py
morepath-0.19.dist-info/LICENSE.txt
morepath-0.19.dist-info/METADATA
morepath-0.19.dist-info/WHEEL
morepath-0.19.dist-info/top_level.txt
morepath-0.19.dist-info/RECORD
