Metadata-Version: 2.1
Name: morepath
Version: 0.19
Summary: A micro web-framework with superpowers
Home-page: http://morepath.readthedocs.io
Author: Morepath developers
Author-email: morepath@googlegroups.com
License: BSD
Keywords: web wsgi routing morepath
Platform: UNKNOWN
Classifier: Intended Audience :: Developers
Classifier: License :: OSI Approved :: BSD License
Classifier: Environment :: Web Environment
Classifier: Topic :: Software Development :: Libraries :: Application Frameworks
Classifier: Topic :: Internet :: WWW/HTTP :: WSGI
Classifier: Programming Language :: Python :: 3.4
Classifier: Programming Language :: Python :: 3.5
Classifier: Programming Language :: Python :: 3.6
Classifier: Programming Language :: Python :: 3.7
Classifier: Programming Language :: Python :: 3.8
Classifier: Programming Language :: Python :: Implementation :: PyPy
Classifier: Development Status :: 5 - Production/Stable
Requires-Dist: setuptools
Requires-Dist: webob (>=1.7.0)
Requires-Dist: reg (>=0.12)
Requires-Dist: dectate (>=0.14)
Requires-Dist: importscan (>=0.2)
Provides-Extra: coverage
Requires-Dist: pytest-cov ; extra == 'coverage'
Provides-Extra: docs
Requires-Dist: sphinx ; extra == 'docs'
Requires-Dist: pyyaml ; extra == 'docs'
Requires-Dist: WebTest (>=2.0.14) ; extra == 'docs'
Provides-Extra: pep8
Requires-Dist: flake8 ; extra == 'pep8'
Requires-Dist: black ; extra == 'pep8'
Provides-Extra: test
Requires-Dist: pytest (>=2.9.0) ; extra == 'test'
Requires-Dist: pytest-remove-stale-bytecode ; extra == 'test'
Requires-Dist: WebTest (>=2.0.14) ; extra == 'test'
